{"cursor":"21990","size":15,"audio":[],"currentlang":"en","article":"An 'electroshock weapon' is an incapacitant weapon used for incapacitating a\nperson by administering electric shock aimed at disrupting superficial muscle\nfunctions.\n\nOne type is a conductive energy device (CED) which fires projectiles that\nadminister the shock through a thin, flexible wire. Other electroshock weapons\nsuch as 'stun guns', 'stun batons', and 'electroshock belts' administer an\nelectric shock by direct contact. A 'shockround' is a piezo-electric tip for a\nprojectile that generates and releases electric charge on impact.\n\n between its two electrodes]] (CGI) of a man holding an electric shock baton]]\n \n","linknr":324,"url":"Electroshock_weapon","recorded":1374864513,"links":["/w/index.php?title=Electroshock_weapon&action=edit","/w/index.php?title=Electroshock_weapon&action=edit","//bits.wikimedia.org/favicon/wikipedia.ico","/w/opensearch_desc.php","//en.wikipedia.org/w/api.php?action=rsd","//creativecommons.org/licenses/by-sa/3.0/","/w/index.php?title=Special:RecentChanges&feed=atom","//bits.wikimedia.org/en.wikipedia.org/load.php?debug=false&lang=en&modules=ext.gadget.DRN-wizard%2CReferenceTooltips%2Ccharinsert%2Cteahouse%7Cext.rtlcite%2Cwikihiero%7Cext.uls.nojs%7Cmediawiki.legacy.commonPrint%2Cshared%7Cmw.PopUpMediaTransform%7Cskins.vector&only=styles&skin=vector&*","//bits.wikimedia.org/en.wikipedia.org/load.php?debug=false&lang=en&modules=site&only=styles&skin=vector&*","//bits.wikimedia.org/en.wikipedia.org/load.php?debug=false&lang=en&modules=startup&only=scripts&skin=vector&*","//bits.wikimedia.org/geoiplookup","//meta.wikimedia.org","#mw-navigation","#p-search","/wiki/Incapacitant","/wiki/Weapon","/wiki/Electric_shock","/wiki/Muscle","/wiki/Piezo-electric","/wiki/File:Taser-x26.jpg","//upload.wikimedia.org/wikipedia/commons/thumb/f/fb/Taser-x26.jpg/220px-Taser-x26.jpg","/wiki/File:Taser-x26.jpg","//bits.wikimedia.org/static-1.22wmf10/skins/common/images/magnify-clip.png","/wiki/Electric_arc","/wiki/Electrode","/wiki/File:Stunbaton_.jpg","//upload.wikimedia.org/wikipedia/commons/thumb/a/a8/Stunbaton_.jpg/220px-Stunbaton_.jpg","/wiki/File:Stunbaton_.jpg","//bits.wikimedia.org/static-1.22wmf10/skins/common/images/magnify-clip.png","/wiki/Computer-generated_image","#History","#Principles_of_operation","#Commercially-available_varieties","#Wireless_long-range_electric_shock_weapon","#Stun_belts","#Electric_shock_prods","#Prototype_designs","#Weapons_that_administer_electric_shock_through_a_stream_of_fluid","#Controversies","#Legal_issues","#Torture","#See_also","#References","#External_links","#Patents","/w/index.php?title=Electroshock_weapon&action=edit&section=1","/wiki/Jack_Cover","/wiki/NASA","/wiki/Taser","#cite_note-1","/wiki/Tom_Swift","/wiki/Tom_Swift_and_His_Electric_Rifle","#cite_note-2","/wiki/Smokeless_powder","/wiki/Bureau_of_Alcohol,_Tobacco_and_Firearms","/wiki/Firearm","#cite_note-stunning_revelations-3","#cite_note-CPSC_236-4","#cite_note-NovaXR5000-5","/w/index.php?title=Electroshock_weapon&action=edit&section=2","/wiki/Pain","#cite_note-6","/wiki/Wikipedia:Citation_needed","/wiki/Wikipedia:Citation_needed","/wiki/Oscillator","/wiki/Resonance","/wiki/Power_inverter","/wiki/Transformer","/wiki/Diode","/wiki/Capacitor","/wiki/Voltage_multiplier","/wiki/Battery_(electricity)","/wiki/Wikipedia:Citation_needed","#cite_note-7","#cite_note-8","#cite_note-9","#cite_note-aaconcerns-10","#cite_note-11","/w/index.php?title=Electroshock_weapon&action=edit&section=3","/wiki/File:Raysun_X-1_img_2865.jpg","//upload.wikimedia.org/wikipedia/commons/thumb/7/71/Raysun_X-1_img_2865.jpg/120px-Raysun_X-1_img_2865.jpg","/wiki/File:Taser_Stoper_C-2_img_2864.jpg","//upload.wikimedia.org/wikipedia/commons/thumb/d/da/Taser_Stoper_C-2_img_2864.jpg/120px-Taser_Stoper_C-2_img_2864.jpg","/wiki/File:Electric_lipstic_img_2872.jpg","//upload.wikimedia.org/wikipedia/commons/thumb/9/92/Electric_lipstic_img_2872.jpg/120px-Electric_lipstic_img_2872.jpg","/wiki/File:Taser_celphone.jpg","//upload.wikimedia.org/wikipedia/commons/thumb/0/0a/Taser_celphone.jpg/90px-Taser_celphone.jpg","/wiki/Mobile_phone","/w/index.php?title=Electroshock_weapon&action=edit&section=4","/wiki/Taser_International","/wiki/12-gauge","/wiki/Shotgun","/wiki/United_States_Department_of_Defense","#cite_note-12","/wiki/2010_Northumbria_Police_manhunt","#cite_note-13","/wiki/United_Kingdom","/wiki/Home_Secretary","/wiki/Theresa_May","#cite_note-14","/w/index.php?title=Leyden_Gun&action=edit&redlink=1","/w/index.php?title=Nova_Technologies&action=edit&redlink=1","/w/index.php?title=Oleg_Nemtyshkin&action=edit&redlink=1","#cite_note-15","/w/index.php?title=Electroshock_weapon&action=edit&section=5","/wiki/Stun_belt","/wiki/REACT_belt","/w/index.php?title=Electroshock_weapon&action=edit&section=6","/wiki/File:Electric_cattle_prod.jpg","//upload.wikimedia.org/wikipedia/commons/thumb/d/d3/Electric_cattle_prod.jpg/220px-Electric_cattle_prod.jpg","/wiki/File:Electric_cattle_prod.jpg","//bits.wikimedia.org/static-1.22wmf10/skins/common/images/magnify-clip.png","/wiki/Cattle_prod","/wiki/Electrodes","/wiki/Flashlight","/w/index.php?title=Electroshock_weapon&action=edit&section=7","/wiki/Electrolaser","/w/index.php?title=Electroshock_weapon&action=edit&section=8","/wiki/Electrified_water_cannon","/wiki/Wikipedia:Citation_needed","/wiki/Rheinmetall_W%26M","/wiki/Aerosol","/wiki/Plasma_(physics)","/wiki/Wikipedia:Citation_needed","/w/index.php?title=Electroshock_weapon&action=edit&section=9","/wiki/Taser_safety_issues","#cite_note-16","#cite_note-17","#cite_note-18","/wiki/Robert_Dzieka%C5%84ski_Taser_incident","#cite_note-19","#cite_note-20","#cite_note-21","#cite_note-22","/w/index.php?title=Electroshock_weapon&action=edit&section=10","/wiki/Germany","/wiki/Gun_politics_in_Germany","#cite_note-23","#cite_note-24","/wiki/Federal_Criminal_Police_Office_(Germany)","#cite_note-25","/wiki/Physikalisch-Technische_Bundesanstalt","#cite_note-26","#cite_note-27","#cite_note-28","/w/index.php?title=Electroshock_weapon&action=edit&section=11","/wiki/United_Nations","#cite_note-29","#cite_note-30","/wiki/Amnesty_International","/wiki/Torture","#cite_note-31","/wiki/Amnesty_International","#cite_note-32","/wiki/Beating_up","/wiki/American_Civil_Liberties_Union","/w/index.php?title=Electroshock_weapon&action=edit&section=12","/wiki/Bug_zapper","/wiki/Electric_fence","/wiki/Fly-killing_device#Electric_flyswatter","/w/index.php?title=Electroshock_weapon&action=edit&section=13","#cite_ref-1","http://www.thestar.com/News/article/281499","#cite_ref-2","http://books.google.com/books?id=P8-oSPHlHXoC","/wiki/International_Standard_Book_Number","/wiki/Special:BookSources/978-0-7506-9630-2","#cite_ref-stunning_revelations_3-0","http://www.inthesetimes.com/site/main/article/2894/","#cite_ref-CPSC_236_4-0","http://www.cpsc.gov/LIBRARY/FOIA/advisory/236.pdf","/wiki/U.S._Consumer_Product_Safety_Commission","#cite_ref-NovaXR5000_5-0","http://books.google.com/books?id=oQAAAAAAMBAJ&pg=PA92","/wiki/International_Standard_Serial_Number","http://www.worldcat.org/search?fq=x0:jrnl&q=n2:01617370","#cite_ref-6","/wiki/Darius_Rejali","http://academic.reed.edu/poli_sci/faculty/rejali/rejali/articles/electric.html","#cite_ref-7","http://www.fool.com/investing/small-cap/2004/11/01/talking-about-taser.aspx","#cite_ref-8","http://www.cnn.com/2004/US/11/14/children.tasers/index.html","#cite_ref-9","http://www.taser.com/SiteCollectionDocuments/Controlled%20Documents/Warnings/LG-INST-LEWARN-001%20REV%20L%20Law%20Enforcement%20Warnings.pdf","#cite_ref-aaconcerns_10-0","http://web.amnesty.org/library/pdf/AMR510302006ENGLISH/$File/AMR5103006.pdf","#cite_ref-11","http://web.amnesty.org/library/Index/ENGAMR511392004","#cite_ref-12","http://www.prnewswire.com/cgi-bin/stories.pl?ACCT=104&STORY=/www/story/02-14-2006/0004281420&EDATE","#cite_ref-13","http://news.bbc.co.uk/1/hi/england/10615302.stm","#cite_ref-14","http://www.dailyexpress.co.uk/posts/view/203025/Taser-guns-chief-kills-himself-after-Raol-Moat-shooting-row/","#cite_ref-15","http://www.wired.co.uk/news/archive/2010-05/21/russian-man-aims-to-reinvent-'taser'-technology","#cite_ref-16","http://www.redorbit.com/news/health/937442/cleveland_clinic_study_demonstrates_taser_x26_does_not_affect_shortterm/index.html?source=r_health","#cite_ref-17","http://www.sciencedaily.com/releases/2007/05/070516071544.htm","#cite_ref-18","http://www.guardian.co.uk/crime/article/0,2763,1583867,00.html","#cite_ref-19","http://www.cbc.ca/canada/british-columbia/story/2009/03/23/bc-robinson-testimony-braidwood-inquiry.html?Authorized=1&AuthenticationKey=2_28_b788caf0-46c8-4335-8ece-f4fe8ba63527.pbcehlmbkeafmo#socialcomments-submit","#cite_ref-20","http://www.cbc.ca/news/pdf/taser-analysis-v1.5.pdf","#cite_ref-21","http://www.highvoltageconnection.com/articles/ElectricShockQuestions.htm","#cite_ref-22","http://www.taser.com/SiteCollectionDocuments/Downloads/MK-INST-X26E-001%20REV%20B%20X26E%20Manual.pdf","#cite_ref-23","http://www.gesetze-im-internet.de/waffg_2002/anlage_2_80.html","#cite_ref-24","http://www.gesetze-im-internet.de/waffg_2002/__40.html","#cite_ref-25","#cite_ref-26","http://www.bka.de/profil/faq/waffenrecht/kennzeichnungspflicht_elektroschocker.html","#cite_ref-27","http://www.bka.de/profil/faq/waffenrecht/av_e-schocker_altbesitz.pdf","#cite_ref-28","http://www.bka.de/profil/faq/waffenrecht/faq-waffenrecht.pdf","#cite_ref-29","http://www.unog.ch/80256EDD006B9C2E/(httpNewsByYear_en)/D3DD9DE87B278A87C125739C0054A81C?OpenDocument","#cite_ref-30","http://www.news.com.au/dailytelegraph/story/0,22049,22814674-5001028,00.html?from=public_rss","#cite_ref-31","http://web.amnesty.org/report2003/usa-summary-eng","#cite_ref-32","http://web.amnesty.org/library/pdf/AMR510302006ENGLISH/$File/AMR5103006.pdf","/w/index.php?title=Electroshock_weapon&action=edit&section=14","http://www.bradford.ac.uk/acad/nlw/research_reports/docs/BNLWRP_electricalweapons_Opinion_Jan06.pdf","http://www.yoursecurityguide.com/physical-effects.aspx","http://www.fbi.gov/publications/leb/2005/mar05leb.pdf","http://electronics.howstuffworks.com/stun-gun.htm","/w/index.php?title=Electroshock_weapon&action=edit&section=15","http://www.google.com/patents/US8843","http://www.google.com/patents/US2805067","http://www.google.com/patents/US5103366","//en.wikipedia.org/w/index.php?title=Special:CentralAutoLogin/start&type=1x1&from=enwiki","http://en.wikipedia.org/w/index.php?title=Electroshock_weapon&oldid=564998789","/wiki/Help:Categories","/wiki/Category:Police_weapons","/wiki/Category:Non-lethal_weapons","/wiki/Category:All_articles_with_unsourced_statements","/wiki/Category:Articles_with_unsourced_statements_from_November_2010","/wiki/Category:Articles_with_unsourced_statements_from_October_2012","/wiki/Category:Articles_with_unsourced_statements_from_July_2013","/w/index.php?title=Special:UserLogin&returnto=Electroshock+weapon&type=signup","/w/index.php?title=Special:UserLogin&returnto=Electroshock+weapon","/wiki/Electroshock_weapon","/wiki/Talk:Electroshock_weapon","#","/wiki/Electroshock_weapon","/w/index.php?title=Electroshock_weapon&action=edit","/w/index.php?title=Electroshock_weapon&action=history","#","/w/index.php","//bits.wikimedia.org/static-1.22wmf10/skins/vector/images/search-ltr.png?303-4","/wiki/Main_Page","/wiki/Main_Page","/wiki/Portal:Contents","/wiki/Portal:Featured_content","/wiki/Portal:Current_events","/wiki/Special:Random","//donate.wikimedia.org/wiki/Special:FundraiserRedirector?utm_source=donate&utm_medium=sidebar&utm_campaign=C13_en.wikipedia.org&uselang=en","/wiki/Help:Contents","/wiki/Wikipedia:About","/wiki/Wikipedia:Community_portal","/wiki/Special:RecentChanges","//en.wikipedia.org/wiki/Wikipedia:Contact_us","/wiki/Special:WhatLinksHere/Electroshock_weapon","/wiki/Special:RecentChangesLinked/Electroshock_weapon","/wiki/Wikipedia:File_Upload_Wizard","/wiki/Special:SpecialPages","/w/index.php?title=Electroshock_weapon&oldid=564998789","/w/index.php?title=Electroshock_weapon&action=info","//www.wikidata.org/wiki/Q870114","/w/index.php?title=Special:Cite&page=Electroshock_weapon&id=564998789","/w/index.php?title=Special:Book&bookcmd=book_creator&referer=Electroshock+weapon","/w/index.php?title=Special:Book&bookcmd=render_article&arttitle=Electroshock+weapon&oldid=564998789&writer=rl","/w/index.php?title=Electroshock_weapon&printable=yes","//ar.wikipedia.org/wiki/%D8%B5%D8%B9%D9%91%D9%82%D8%A9","//bg.wikipedia.org/wiki/%D0%95%D0%BB%D0%B5%D0%BA%D1%82%D1%80%D0%BE%D1%88%D0%BE%D0%BA%D0%BE%D0%B2%D0%BE_%D0%BE%D1%80%D1%8A%D0%B6%D0%B8%D0%B5","//ca.wikipedia.org/wiki/Arma_d%27electroxoc","//cs.wikipedia.org/wiki/Taser","//da.wikipedia.org/wiki/Elektrochokv%C3%A5ben","//de.wikipedia.org/wiki/Elektroimpulswaffe","//es.wikipedia.org/wiki/Arma_de_electrochoque","//eo.wikipedia.org/wiki/Elektro%C5%9Doka_armilo","//fa.wikipedia.org/wiki/%D8%A8%D8%A7%D8%AA%D9%88%D9%85_%D8%A8%D8%B1%D9%82%DB%8C","//fr.wikipedia.org/wiki/Pistolet_%C3%A0_impulsion_%C3%A9lectrique","//ko.wikipedia.org/wiki/%EC%A0%84%EC%9E%90%EC%B6%A9%EA%B2%A9%EA%B8%B0","//io.wikipedia.org/wiki/Pistolo_per_elektroza_impulso","//it.wikipedia.org/wiki/Taser","//he.wikipedia.org/wiki/%D7%A9%D7%95%D7%A7%D7%A8_%D7%97%D7%A9%D7%9E%D7%9C%D7%99","//nl.wikipedia.org/wiki/Stroomstootwapen","//ja.wikipedia.org/wiki/%E3%82%B9%E3%82%BF%E3%83%B3%E3%82%AC%E3%83%B3","//no.wikipedia.org/wiki/Elektrosjokkv%C3%A5pen","//pl.wikipedia.org/wiki/Paralizator","//pt.wikipedia.org/wiki/Arma_de_eletrochoque","//ru.wikipedia.org/wiki/%D0%AD%D0%BB%D0%B5%D0%BA%D1%82%D1%80%D0%BE%D1%88%D0%BE%D0%BA%D0%BE%D0%B2%D0%BE%D0%B5_%D0%BE%D1%80%D1%83%D0%B6%D0%B8%D0%B5","//simple.wikipedia.org/wiki/Taser","//fi.wikipedia.org/wiki/Et%C3%A4lamautin","//sv.wikipedia.org/wiki/Elchockvapen","//th.wikipedia.org/wiki/%E0%B9%80%E0%B8%84%E0%B8%A3%E0%B8%B7%E0%B9%88%E0%B8%AD%E0%B8%87%E0%B8%8A%E0%B9%8A%E0%B8%AD%E0%B8%95%E0%B9%84%E0%B8%9F%E0%B8%9F%E0%B9%89%E0%B8%B2","//zh-yue.wikipedia.org/wiki/%E9%9B%BB%E6%A7%8D","//zh.wikipedia.org/wiki/%E9%9B%BB%E6%A7%8D","#","//www.wikidata.org/wiki/Q870114#sitelinks-wikipedia","//en.wikipedia.org/wiki/Wikipedia:Text_of_Creative_Commons_Attribution-ShareAlike_3.0_Unported_License","//creativecommons.org/licenses/by-sa/3.0/","//wikimediafoundation.org/wiki/Terms_of_Use","//wikimediafoundation.org/wiki/Privacy_policy","//www.wikimediafoundation.org/","//wikimediafoundation.org/wiki/Privacy_policy","/wiki/Wikipedia:About","/wiki/Wikipedia:General_disclaimer","//en.wikipedia.org/wiki/Wikipedia:Contact_us","//en.m.wikipedia.org/wiki/Electroshock_weapon","//wikimediafoundation.org/","//bits.wikimedia.org/images/wikimedia-button.png","//www.mediawiki.org/","//bits.wikimedia.org/static-1.22wmf10/skins/common/images/poweredby_mediawiki_88x31.png","//bits.wikimedia.org/en.wikipedia.org/load.php?debug=false&lang=en&modules=site&only=scripts&skin=vector&*"],"instances":["physics","electricity","germany"],"pdf":["http://www.cpsc.gov/LIBRARY/FOIA/advisory/236.pdf","http://www.taser.com/SiteCollectionDocuments/Controlled%20Documents/Warnings/LG-INST-LEWARN-001%20REV%20L%20Law%20Enforcement%20Warnings.pdf","http://web.amnesty.org/library/pdf/AMR510302006ENGLISH/$File/AMR5103006.pdf","http://www.cbc.ca/news/pdf/taser-analysis-v1.5.pdf","http://www.taser.com/SiteCollectionDocuments/Downloads/MK-INST-X26E-001%20REV%20B%20X26E%20Manual.pdf","http://www.bka.de/profil/faq/waffenrecht/av_e-schocker_altbesitz.pdf","http://www.bka.de/profil/faq/waffenrecht/faq-waffenrecht.pdf","http://web.amnesty.org/library/pdf/AMR510302006ENGLISH/$File/AMR5103006.pdf","http://www.bradford.ac.uk/acad/nlw/research_reports/docs/BNLWRP_electricalweapons_Opinion_Jan06.pdf","http://www.fbi.gov/publications/leb/2005/mar05leb.pdf"],"categories":["Police weapons","Non-lethal weapons"],"headings":["History","Principles of operation","Commercially-available varieties","Prototype designs","Controversies","See also","References","External links"],"image":["//upload.wikimedia.org/wikipedia/commons/thumb/f/fb/Taser-x26.jpg/220px-Taser-x26.jpg","//bits.wikimedia.org/static-1.22wmf10/skins/common/images/magnify-clip.png","//upload.wikimedia.org/wikipedia/commons/thumb/a/a8/Stunbaton_.jpg/220px-Stunbaton_.jpg","//bits.wikimedia.org/static-1.22wmf10/skins/common/images/magnify-clip.png","//upload.wikimedia.org/wikipedia/commons/thumb/7/71/Raysun_X-1_img_2865.jpg/120px-Raysun_X-1_img_2865.jpg","//upload.wikimedia.org/wikipedia/commons/thumb/d/da/Taser_Stoper_C-2_img_2864.jpg/120px-Taser_Stoper_C-2_img_2864.jpg","//upload.wikimedia.org/wikipedia/commons/thumb/9/92/Electric_lipstic_img_2872.jpg/120px-Electric_lipstic_img_2872.jpg","//upload.wikimedia.org/wikipedia/commons/thumb/0/0a/Taser_celphone.jpg/90px-Taser_celphone.jpg","//upload.wikimedia.org/wikipedia/commons/thumb/d/d3/Electric_cattle_prod.jpg/220px-Electric_cattle_prod.jpg","//bits.wikimedia.org/static-1.22wmf10/skins/common/images/magnify-clip.png","//en.wikipedia.org/w/index.php?title=Special:CentralAutoLogin/start&type=1x1&from=enwiki","//bits.wikimedia.org/static-1.22wmf10/skins/vector/images/search-ltr.png?303-4","//bits.wikimedia.org/images/wikimedia-button.png","//bits.wikimedia.org/static-1.22wmf10/skins/common/images/poweredby_mediawiki_88x31.png"],"tags":[["battery","electricity"],["plasma","physics"],["federal_criminal_police_office","germany"]],"members":["plasma","battery","federal_criminal_police_office"],"related":["Incapacitant","Weapon","Electric_shock","Muscle","Piezo-electric","Electrode","Jack_Cover","NASA","Taser","Tom_Swift","Tom_Swift_and_His_Electric_Rifle","Smokeless_powder","Bureau_of_Alcohol,_Tobacco_and_Firearms","Firearm","U.S._Consumer_Product_Safety_Commission","Pain","Darius_Rejali","Oscillator","Resonance","Power_inverter","Transformer","Diode","Capacitor","Voltage_multiplier","Battery_(electricity)","Mobile_phone","Taser_International","12-gauge","Shotgun","United_States_Department_of_Defense","2010_Northumbria_Police_manhunt","United_Kingdom","Home_Secretary","Theresa_May","Leyden_Gun","Nova_Technologies","Oleg_Nemtyshkin","REACT_belt","Cattle_prod","Electrodes","Flashlight","Electrolaser","Electrified_water_cannon","Rheinmetall_W&M","Aerosol","Plasma_(physics)","Robert_Dziekański_Taser_incident","Germany","Gun_politics_in_Germany","Federal_Criminal_Police_Office_(Germany)","Physikalisch-Technische_Bundesanstalt","United_Nations","Amnesty_International","Torture","Amnesty_International","Beating_up","American_Civil_Liberties_Union","Bug_zapper","Electric_fence"]}