{"cursor":"92802","size":15,"audio":[],"currentlang":"en","article":"\n\n\n[[Star Trek: The Next Generation]] is an American science fiction television\nseries which aired in syndication from September 1987 through May 1994. It is\nthe second live action series of the [[Star Trek]] franchise, and comprises a\ntotal of 178 episodes over seven seasons. The series picks up about 100 years\nafter takes place.\n\nThe cast for the show's seven seasons consisted of Patrick Stewart as captain\nJean-Luc Picard, Jonathan Frakes as his second-in-command William Riker, Brent\nSpiner as the android Data, LeVar Burton as chief engineer Geordi LaForge,\nMarina Sirtis as counselor Deanna Troi, Michael Dorn as the Klingon Worf, and\nGates McFadden as Dr. Beverly Crusher. McFadden left the show after the first\nseason and was replaced with Diana Muldaur, but McFadden returned for the third\nseason and would remain with the cast until the series finale. Wil Wheaton\nstarred as Wesley Crusher in seasons 1â4, returning for guest appearances in\nseasons 5 and 7. Denise Crosby played chief security officer Tasha Yar in the\nfirst season but was killed off in the episode \"Skin of Evil\". Crosby would\nreturn for several guest appearances in later seasons.\n\nThe Next Generation cast also appears in four feature films, [[Star Trek\nGenerations|Generations]], [[Star Trek: First Contact|First Contact]], [[Star\nTrek: Insurrection|Insurrection]], and [[Star Trek Nemesis|Nemesis]].\n\nThe television episodes are listed here in chronological order by original air\ndate, which match the episode order in each season's DVD set. This list also\nincludes the stardate on which the events of each episode took place within the\nfictional Star Trek universe.\n","linknr":1568,"url":"Star_Trek_The_Next_Generation_DVD","recorded":1362534928,"links":47,"instances":["star_trek","star_trek","star_trek","star_trek_character","star_trek","star_trek","actor","writer","author","director","star_trek","director","star_trek","space_station","star_trek","star_trek","nautical","screenwriter","writer","director","producer","star_trek","star_trek","filmmaker"],"pdf":[],"categories":["Star Trek episode lists|Next Generation, The","Star Trek","Lists of science fiction television series episodes|Star Trek"],"headings":["Series overview","Episodes","See also","References","External links"],"image":["//upload.wikimedia.org/wikipedia/commons/thumb/4/46/Star_Trek_TNG_logo.svg/300px-Star_Trek_TNG_logo.svg.png","//upload.wikimedia.org/wikipedia/commons/thumb/d/d6/Wikiquote-logo-en.svg/40px-Wikiquote-logo-en.svg.png","//upload.wikimedia.org/wikipedia/commons/thumb/8/89/Symbol_book_class2.svg/16px-Symbol_book_class2.svg.png","//upload.wikimedia.org/wikipedia/en/thumb/4/48/Folder_Hexagonal_Icon.svg/16px-Folder_Hexagonal_Icon.svg.png","//upload.wikimedia.org/wikipedia/en/thumb/f/fd/Portal-puzzle.svg/16px-Portal-puzzle.svg.png","//upload.wikimedia.org/wikipedia/commons/thumb/3/37/People_icon.svg/16px-People_icon.svg.png","//bits.wikimedia.org/static-1.21wmf10/skins/vector/images/search-ltr.png?303-4","//bits.wikimedia.org/images/wikimedia-button.png","//bits.wikimedia.org/static-1.21wmf10/skins/common/images/poweredby_mediawiki_88x31.png"],"tags":[["data","star_trek"],["rob_bowman","filmmaker"],["guinan","star_trek_character"],["rob_bowman","filmmaker"],["data","star_trek"],["data","star_trek"],["data","star_trek"],["data","star_trek"],["larry_shaw","director"],["hans_beimler","screenwriter"],["data","star_trek"],["data","star_trek"],["paul_lynch","director"],["rob_bowman","filmmaker"],["data","star_trek"],["data","star_trek"],["rob_bowman","filmmaker"],["data","star_trek"],["data","star_trek"],["data","star_trek"],["data","star_trek"],["rob_bowman","filmmaker"],["q","star_trek"],["borg","star_trek"],["rob_bowman","filmmaker"],["hans_beimler","screenwriter"],["hans_beimler","screenwriter"],["david_kemper","writer"],["data","star_trek"],["rob_bowman","filmmaker"],["hans_beimler","screenwriter"],["data","star_trek"],["data","star_trek"],["john_anderson","actor"],["hans_beimler","screenwriter"],["david_carson","director"],["david_kemper","writer"],["q","star_trek"],["q","star_trek"],["david_carson","director"],["hans_beimler","screenwriter"],["guinan","star_trek_character"],["data","star_trek"],["data","star_trek"],["uss_enterprise","ncc-1701-d"],["hans_beimler","screenwriter"],["vash","star_trek"],["data","star_trek"],["data","star_trek"],["vulcan","star_trek"],["borg","star_trek"],["borg","star_trek"],["rob_bowman","filmmaker"],["data","star_trek"],["lore","star_trek"],["data","star_trek"],["lore","star_trek"],["lee_sheldon","writer"],["data","star_trek"],["thomas_perry","author"],["thomas_perry","author"],["data","star_trek"],["miles_o'brien","star_trek"],["data","star_trek"],["miles_o'brien","star_trek"],["miles_o'brien","star_trek"],["data","star_trek"],["vash","star_trek"],["q","star_trek"],["q","star_trek"],["data","star_trek"],["data","star_trek"],["david_carson","director"],["data","star_trek"],["sela","star_trek"],["data","star_trek"],["data","star_trek"],["data","star_trek"],["sela","star_trek"],["vulcan","star_trek"],["paul_lynch","director"],["data","star_trek"],["data","star_trek"],["herbert_wright","producer"],["data","star_trek"],["miles_o'brien","star_trek"],["miles_o'brien","star_trek"],["data","star_trek"],["paul_lynch","director"],["borg","star_trek"],["david_carson","director"],["transporter","star_trek"],["data","star_trek"],["data","star_trek"],["uss_enterprise","ncc-1701-d"],["q","star_trek"],["q","star_trek"],["guinan","star_trek_character"],["data","star_trek"],["data","star_trek"],["data","star_trek"],["data","star_trek"],["data","star_trek"],["q","star_trek"],["q","star_trek"],["data","star_trek"],["deep_space_nine","space_station"],["data","star_trek"],["data","star_trek"],["borg","star_trek"],["vulcan","star_trek"],["data","star_trek"],["warp_drive","star_trek"],["data","star_trek"],["data","star_trek"],["data","star_trek"],["data","star_trek"],["bridge","nautical"],["data","star_trek"],["data","star_trek"],["data","star_trek"],["maquis","star_trek"],["q","star_trek"],["q","star_trek"]],"members":["lore","maquis","guinan","vulcan","vash","uss_enterprise","john_anderson","david_kemper","thomas_perry","larry_shaw","borg","david_carson","warp_drive","deep_space_nine","sela","data","bridge","hans_beimler","lee_sheldon","paul_lynch","herbert_wright","q","transporter","rob_bowman"],"related":["List_of_science_fiction_television_programs","Broadcast_syndication","Patrick_Stewart","Jean-Luc_Picard","Jonathan_Frakes","William_Riker","Brent_Spiner","Data_(Star_Trek)","LeVar_Burton","Geordi_LaForge","Marina_Sirtis","Deanna_Troi","Michael_Dorn","Worf","Gates_McFadden","Beverly_Crusher","Diana_Muldaur","Wil_Wheaton","Wesley_Crusher","Denise_Crosby","Tasha_Yar","Skin_of_Evil","Stardate","Amazon.co.uk","Blu-ray_Disc","Encounter_at_Farpoint","All_Good_Things...","Rob_Bowman_(filmmaker)","Jon_Povill","Deanna_Troi","Katherine_Pulaski","Guinan_(Star_Trek_character)","Katherine_Pulaski","Geordi_La_Forge","Deanna_Troi","Where_Silence_Has_Lease","Winrich_Kolbe","Jack_B._Sowards","Elementary,_Dear_Data","Rob_Bowman_(filmmaker)","Data_(Star_Trek)","Geordi_LaForge","Katherine_Pulaski","Data_(Star_Trek)","Sherlock_Holmes","Holodeck","Geordi_LaForge","Sherlock_Holmes","Professor_Moriarty","The_Outrageous_Okona","Robert_Becker","Burton_Armus","Lance_Dickson","David_Landsberg","Data_(Star_Trek)","Data_(Star_Trek)","Joe_Piscopo","Loud_as_a_Whisper","Larry_Shaw_(director)","Les_Landau","Tracy_Tormé","Hans_Beimler_(screenwriter)","Data_(Star_Trek)","Data_(Star_Trek)","Paul_Lynch_(director)","Mike_Gray","Katherine_Pulaski","A_Matter_of_Honor","Rob_Bowman_(filmmaker)","Burton_Armus","Burton_Armus","William_Riker","William_Riker","Klingon","Robert_Scheerer","Melinda_M._Snodgrass","Jean-Luc_Picard","Data_(Star_Trek)","Data_(Star_Trek)","United_Federation_of_Planets","Amanda_McBroom","The_Dauphin","Rob_Bowman_(filmmaker)","Scott_Rubenstein","Leonard_Mlodinow","Wesley_Crusher","Wesley_Crusher","Paddi_Edwards","Joseph_L._Scanlan","Steve_Gerber","The_Royale","Cliff_Bole","Tracy_Tormé","William_Riker","Data_(Star_Trek)","Worf","William_Riker","Worf","Data_(Star_Trek)","Gas_giant","Joseph_L._Scanlan","Jean-Luc_Picard","Jean-Luc_Picard","The_Icarus_Factor","Robert_Iscove","William_Riker","Worf","William_Riker","Worf","Winrich_Kolbe","Melinda_M._Snodgrass","Data_(Star_Trek)","Wesley_Crusher","Prime_Directive","Data_(Star_Trek)","Q_Who","Rob_Bowman_(filmmaker)","Q_(Star_Trek)","Borg_(Star_Trek)","Samaritan_Snare","Les_Landau","Geordi_La_Forge","Pakled","Geordi_La_Forge","Up_the_Long_Ladder","Winrich_Kolbe","Melinda_M._Snodgrass","Jean-Luc_Picard","Rob_Bowman_(filmmaker)","Tracy_Tormé","Jean-Luc_Picard","Deanna_Troi","Lwaxana_Troi","Deanna_Troi","Lwaxana_Troi","Jean-Luc_Picard","Cliff_Bole","Hans_Beimler_(screenwriter)","Hans_Beimler_(screenwriter)","Worf","Worf","Klingon","Robert_Scheerer","David_Kemper_(writer)","Data_(Star_Trek)","Strategema","Rob_Bowman_(filmmaker)","Hans_Beimler_(screenwriter)","William_Riker","Deanna_Troi","Katherine_Pulaski","William_Riker","1988_Writers_Guild_of_America_strike","Winrich_Kolbe","Michael_Piller","Michael_Piller","Wesley_Crusher","Nanorobotics","Wesley_Crusher","Ken_Jenkins","The_Ensigns_of_Command","Cliff_Bole","Melinda_M._Snodgrass","Data_(Star_Trek)","Data_(Star_Trek)","Les_Landau","John_Anderson_(actor)","Anne_Haney","Who_Watches_the_Watchers","Robert_Wiemer","Hans_Beimler_(screenwriter)","Jean-Luc_Picard","William_Riker","Deanna_Troi","The_Bonding","Winrich_Kolbe","Ronald_D._Moore","Gabriel_Damon","Gabrielle_Beaumont","Michael_Piller","Geordi_La_Forge","Booby_trap","Holodeck","United_Federation_of_Planets","Susan_Gibney","David_Carson_(director)","David_Kemper_(writer)","Michael_Piller","Geordi_La_Forge","Geordi_La_Forge","Romulan","Robert_Scheerer","Deanna_Troi","Deanna_Troi","Wormhole","Dan_Shor","The_Vengeance_Factor","Sam_Rolfe","William_Riker","William_Riker","Robert_Scheerer","Ronald_D._Moore","Romulan","Jean-Luc_Picard","Cliff_Bole","United_Federation_of_Planets","James_Cromwell","Gabrielle_Beaumont","Melinda_M._Snodgrass","Jean-Luc_Picard","Beverly_Crusher","Beverly_Crusher","Déjà_Q","Les_Landau","Q_(Star_Trek)","Q_Continuum","Q_(Star_Trek)","A_Matter_of_Perspective","Cliff_Bole","Jean-Luc_Picard","William_Riker","William_Riker","Holodeck","Yesterday's_Enterprise","David_Carson_(director)","Ira_Steven_Behr","Hans_Beimler_(screenwriter)","Ronald_D._Moore","Eric_A._Stillwell","Jean-Luc_Picard","Tasha_Yar","Guinan_(Star_Trek_character)","Tasha_Yar","Jonathan_Frakes","René_Echevarria","Data_(Star_Trek)","Data_(Star_Trek)","Gynoid","Starfleet","USS_Enterprise_(NCC-1701-D)","Hallie_Todd","Les_Landau","Ronald_D._Moore","Worf","Worf","Winrich_Kolbe","Hans_Beimler_(screenwriter)","Jean-Luc_Picard","Jean-Luc_Picard","Pulsar","Captain's_Holiday","Chip_Chalmers","Ira_Steven_Behr","Jean-Luc_Picard","Vash_(Star_Trek)","Jean-Luc_Picard","Max_Grodénchik","Robert_Scheerer","David_Bischoff","Deanna_Troi","Deanna_Troi","Romulan","Hollow_Pursuits","Cliff_Bole","Sally_Caves","Reginald_Barclay","Reginald_Barclay","Holodeck","The_Most_Toys","Data_(Star_Trek)","Data_(Star_Trek)","Saul_Rubinek","Les_Landau","Peter_S._Beagle","Jake_Jacobs","Jean-Luc_Picard","Sarek","Vulcan_(Star_Trek)","Sarek","Jean-Luc_Picard","United_Federation_of_Planets","Legaran","Ménage_à_Troi","Fred_Bronson","Susan_Sackett","William_Riker","Deanna_Troi","Lwaxana_Troi","Ferengi","Deanna_Troi","Lwaxana_Troi","William_Riker","Transfigurations","René_Echevarria","Beverly_Crusher","Amnesia","Cliff_Bole","Michael_Piller","Jean-Luc_Picard","Borg_(Star_Trek)","United_Federation_of_Planets","Cliff_Bole","Michael_Piller","Jean-Luc_Picard","Borg_(Star_Trek)","Elizabeth_Dennehy","Les_Landau","Ronald_D._Moore","Jean-Luc_Picard","Worf","Jean-Luc_Picard","Worf","Beverly_Crusher","Wesley_Crusher","Rob_Bowman_(filmmaker)","Rick_Berman","Data_(Star_Trek)","Lore_(Star_Trek)","Data_(Star_Trek)","Noonien_Soong","Lore_(Star_Trek)","Suddenly_Human","Gabrielle_Beaumont","Jeri_Taylor","Jean-Luc_Picard","Jean-Luc_Picard","Lee_Sheldon_(writer)","Beverly_Crusher","Beverly_Crusher","Robert_Scheerer","Joe_Menosky","Data_(Star_Trek)","Tasha_Yar","Jonathan_Frakes","Thomas_Perry_(author)","Ronald_D._Moore","Brannon_Braga","Thomas_Perry_(author)","Jean-Luc_Picard","Worf","Worf","Jean-Luc_Picard","Klingon","Future_Imperfect","Les_Landau","William_Riker","William_Riker","Final_Mission","Corey_Allen","Jeri_Taylor","Jean-Luc_Picard","Wesley_Crusher","Wesley_Crusher","Jean-Luc_Picard","The_Loss","Chip_Chalmers","Deanna_Troi","Deanna_Troi","Data's_Day","Robert_Wiemer","Ronald_D._Moore","Data_(Star_Trek)","Miles_O'Brien_(Star_Trek)","Keiko_O'Brien","Data_(Star_Trek)","Miles_O'Brien_(Star_Trek)","Romulan","Chip_Chalmers","Jeri_Taylor","Stuart_Charno","Jean-Luc_Picard","Miles_O'Brien_(Star_Trek)","Starfleet","Cardassian","Philip_LaZebnik","Philip_LaZebnik","William_Douglas_Lansford","Jean-Luc_Picard","Jean-Luc_Picard","Marta_DuBois","Les_Landau","Joe_Menosky","Data_(Star_Trek)","Wormhole","Cliff_Bole","David_Bischoff","Joe_Menosky","Ronald_D._Moore","Michael_Piller","Marc_Scott_Zicree","William_Riker","William_Riker","Xenophobia","Galaxy's_Child","Winrich_Kolbe","Geordi_La_Forge","Holodeck","Susan_Gibney","Les_Landau","Pamela_Douglas","Jeri_Taylor","Deanna_Troi","Winrich_Kolbe","Brannon_Braga","Geordi_La_Forge","Geordi_La_Forge","Joe_Menosky","Reginald_Barclay","Reginald_Barclay","Qpid","Cliff_Bole","Ira_Steven_Behr","Ira_Steven_Behr","Jean-Luc_Picard","Vash_(Star_Trek)","Q_(Star_Trek)","Q_(Star_Trek)","Jean-Luc_Picard","The_Drumhead","Jonathan_Frakes","Jeri_Taylor","Jean-Luc_Picard","Romulan","Jean_Simmons","Les_Landau","Peter_Allan_Fields","Ted_Roberts","Peter_Allan_Fields","Lwaxana_Troi","Lwaxana_Troi","David_Ogden_Stiers","Marvin_V._Rush","Beverly_Crusher","Beverly_Crusher","David_Livingston","René_Echevarria","René_Echevarria","Geordi_La_Forge","Romulan","Geordi_La_Forge","Patrick_Stewart","Joe_Menosky","Ronald_D._Moore","Data_(Star_Trek)","Data_(Star_Trek)","Cliff_Bole","Jean-Luc_Picard","Worf","Gowron","Ronald_D._Moore","Worf","Gowron","David_Carson_(director)","Ronald_D._Moore","Jean-Luc_Picard","Data_(Star_Trek)","Worf","Sela_(Star_Trek)","Gowron","Darmok","Winrich_Kolbe","Joe_Menosky","Philip_LaZebnik","Joe_Menosky","Jean-Luc_Picard","Jean-Luc_Picard","Paul_Winfield","Les_Landau","Michael_Piller","Rick_Berman","Michael_Piller","Jean-Luc_Picard","Ro_Laren","Jean-Luc_Picard","Bajoran","Ro_Laren","Silicon_Avatar","Cliff_Bole","Jeri_Taylor","Data_(Star_Trek)","Crystalline_Entity","Gabrielle_Beaumont","Ronald_D._Moore","Ron_Jarvis","Deanna_Troi","Corey_Allen","Brannon_Braga","Susan_Sackett","Fred_Bronson","Brannon_Braga","Wesley_Crusher","Wesley_Crusher","Ashley_Judd","Les_Landau","Jeri_Taylor","Rick_Berman","Michael_Piller","Jean-Luc_Picard","Data_(Star_Trek)","Sarek","Spock","Cliff_Bole","Michael_Piller","Rick_Berman","Michael_Piller","Jean-Luc_Picard","Data_(Star_Trek)","Spock","Sela_(Star_Trek)","Vulcan_(Star_Trek)","Romulan","Paul_Lynch_(director)","Rick_Berman","Nuclear_winter","Matt_Frewer","Robert_Scheerer","Grant_Rosenberg","Stuart_Charno","Worf","Alexander_Rozhenko","Worf","Patrick_Stewart","Joe_Menosky","Data_(Star_Trek)","Data_(Star_Trek)","Robert_Wiemer","Jeri_Taylor","Deanna_Troi","Deanna_Troi","Beverly_Crusher","William_Riker","The_Masterpiece_Society","Winrich_Kolbe","Michael_Piller","James_Kahn","Jean-Luc_Picard","Deanna_Troi","Geordi_La_Forge","Eugenics","Paul_Schiffer","David_Livingston","René_Balcer","Herbert_Wright_(producer)","Brannon_Braga","Deanna_Troi","Data_(Star_Trek)","Miles_O'Brien_(Star_Trek)","Deanna_Troi","Miles_O'Brien_(Star_Trek)","Data_(Star_Trek)","Chip_Chalmers","Ronald_D._Moore","Stuart_Charno","Beverly_Crusher","Worf","Worf","Beverly_Crusher","Robert_Scheerer","Jeri_Taylor","William_Riker","William_Riker","Androgyny","Jonathan_Frakes","Brannon_Braga","Kelsey_Grammer","The_First_Duty","Paul_Lynch_(director)","Ronald_D._Moore","Naren_Shankar","Wesley_Crusher","Wesley_Crusher","Starfleet_Academy","Ray_Walston","Winrich_Kolbe","Peter_Allan_Fields","Deanna_Troi","Worf","Lwaxana_Troi","Alexander_Rozhenko","Deanna_Troi","Lwaxana_Troi","The_Perfect_Mate","Cliff_Bole","Michael_Piller","René_Echevarria","Jean-Luc_Picard","Jean-Luc_Picard","Famke_Janssen","Brannon_Braga","I,_Borg","René_Echevarria","Jean-Luc_Picard","Geordi_La_Forge","Borg_(Star_Trek)","Jean-Luc_Picard","Computer_virus","The_Next_Phase","David_Carson_(director)","Ronald_D._Moore","Geordi_La_Forge","Ro_Laren","Transporter_(Star_Trek)","Geordi_La_Forge","Ro_Laren","Peter_Lauritson","Morgan_Gendel","Peter_Allan_Fields","Morgan_Gendel","Jean-Luc_Picard","Jean-Luc_Picard","Joe_Menosky","Michael_Piller","Joe_Menosky","Data_(Star_Trek)","Les_Landau","Jeri_Taylor","Joe_Menosky","Data_(Star_Trek)","Mark_Twain","Jack_London","Jerry_Hardin","Realm_of_Fear","Cliff_Bole","Brannon_Braga","Reginald_Barclay","Reginald_Barclay","Winrich_Kolbe","Deanna_Troi","Deanna_Troi","Alexander_Singer","Ronald_D._Moore","Geordi_La_Forge","Montgomery_Scott","Dyson_sphere","Montgomery_Scott","USS_Enterprise_(NCC-1701-D)","Robert_Wiemer","Brannon_Braga","True_Q","Robert_Scheerer","René_Echevarria","Q_(Star_Trek)","Q_(Star_Trek)","Kansas","Olivia_d'Abo","Adam_Nimoy","Michael_Piller","Jean-Luc_Picard","Ro_Laren","Keiko_O'Brien","Guinan_(Star_Trek_character)","Jean-Luc_Picard","Keiko_O'Brien","Ro_Laren","Guynan","A_Fistful_of_Datas","Patrick_Stewart","Robert_Hewitt_Wolfe","Brannon_Braga","Robert_Hewitt_Wolfe","Deanna_Troi","Data_(Star_Trek)","Worf","Alexander_Rozhenko","Data_(Star_Trek)","Holodeck","Jonathan_Frakes","Naren_Shankar","Jean-Luc_Picard","Data_(Star_Trek)","Data_(Star_Trek)","Ronald_D._Moore","Jean-Luc_Picard","Beverly_Crusher","Worf","Jean-Luc_Picard","Cardassian","Ronny_Cox","Jean-Luc_Picard","Jean-Luc_Picard","Cardassian","René_Echevarria","Jean-Luc_Picard","Data_(Star_Trek)","Reginald_Barclay","Reginald_Barclay","Professor_Moriarty","Holodeck","Daniel_Davis","Aquiel","Brannon_Braga","Ronald_D._Moore","Jeri_Taylor","Geordi_La_Forge","Geordi_La_Forge","Starfleet","Renée_Jones","Gabrielle_Beaumont","Naren_Shankar","René_Echevarria","Deanna_Troi","Deanna_Troi","Romulan","Les_Landau","Ronald_D._Moore","Jean-Luc_Picard","Q_(Star_Trek)","Jean-Luc_Picard","Q_(Star_Trek)","Winrich_Kolbe","Brannon_Braga","Data_(Star_Trek)","Worf","Julian_Bashir","Worf","Deep_Space_Nine_(space_station)","Romulan","Data_(Star_Trek)","James_Cromwell","Dan_Curry","René_Echevarria","Worf","Worf","Starship_Mine","Cliff_Bole","Morgan_Gendel","Jean-Luc_Picard","List_of_fictional_elements,_materials,_isotopes_and_atomic_particles","Starship_Mine","Starship_Mine","Jean-Luc_Picard","Jean-Luc_Picard","Jonathan_Frakes","Joe_Menosky","Jean-Luc_Picard","Beverly_Crusher","Jean-Luc_Picard","Archaeology","Norman_Lloyd","James_L._Conway","William_Riker","William_Riker","Beverly_Crusher","Beverly_Crusher","Ferengi","Rightful_Heir","Worf","Kahless","Klingon","LeVar_Burton","William_Riker","Deanna_Troi","William_Riker","Jean-Luc_Picard","Deanna_Troi","Data_(Star_Trek)","Geordi_La_Forge","Romulan","Borg_(Star_Trek)","Stephen_Hawking","Alexander_Singer","René_Echevarria","Cliff_Bole","Jean-Luc_Picard","Deanna_Troi","Worf","Robert_Wiemer","Joe_Menosky","Geordi_La_Forge","Geordi_La_Forge","Peter_Lauritson","Naren_Shankar","Jean-Luc_Picard","William_Riker","William_Riker","Ronald_D._Moore","Jean-Luc_Picard","William_Riker","Jean-Luc_Picard","William_Riker","Vulcan_(Star_Trek)","Patrick_Stewart","Brannon_Braga","Jean-Luc_Picard","Data_(Star_Trek)","Geordi_La_Forge","Dark_Page","Les_Landau","Deanna_Troi","Lwaxana_Troi","Lwaxana_Troi","Deanna_Troi","Kirsten_Dunst","Attached","Jonathan_Frakes","Jean-Luc_Picard","Beverly_Crusher","Jean-Luc_Picard","Beverly_Crusher","Warp_drive_(Star_Trek)","Robert_Scheerer","Dan_Koeppel","Data_(Star_Trek)","Data_(Star_Trek)","Worf","Worf","LeVar_Burton","William_Riker","William_Riker","Cover-up","Terry_O'Quinn","William_N._Stape","Worf","Worf","Prime_Directive","Jeri_Taylor","Beverly_Crusher","Beverly_Crusher","Lower_Decks","Gabrielle_Beaumont","Alyssa_Ogawa","Cardassian","Thine_Own_Self","Winrich_Kolbe","Deanna_Troi","Data_(Star_Trek)","Data_(Star_Trek)","Deanna_Troi","Bridge_(nautical)","Jean-Luc_Picard","Data_(Star_Trek)","Data_(Star_Trek)","Deanna_Troi","Deanna_Troi","Gates_McFadden","Jean-Luc_Picard","Data_(Star_Trek)","Jean-Luc_Picard","Corey_Allen","Shawn_Piller","Wesley_Crusher","Wesley_Crusher","Indigenous_peoples_of_the_Americas","Cardassian","Richard_Poe","Eric_Menyuk","Worf","Alexander_Rozhenko","Worf","James_Sloyan","Jean-Luc_Picard","Jean-Luc_Picard","Lee_Arenberg","Ro_Laren","Ro_Laren","Jean-Luc_Picard","Maquis_(Star_Trek)","Richard_Poe","All_Good_Things...","Jean-Luc_Picard","Q_(Star_Trek)","Jean-Luc_Picard","Q_(Star_Trek)","List_of_Star_Trek_characters"]}