{"cursor":"8595","size":15,"audio":[],"currentlang":"en","article":"'DETAIL' is the international professional journal for architecture and\nconstruction details produced by Detail publishers. Each issue deals with a\nspecific aspect of building, such as concrete construction, roof structures or\nrefurbishment, whereby emphasis is placed on the quality of the building\ndetails. Up-to-date examples are selected from schemes around the world, and\nthese are illustrated with plans and details drawn to a consistent scale as well\nas with photographs. The journal focuses on the depiction of new developments in\nthe form of descriptive texts, constructional drawings and photos. The target\ngroup comprises above all architects, engineers and other specialists from the\nfield of construction.\n","linknr":165,"url":"DETAIL_(professional_journal)","recorded":1362889687,"links":19,"instances":[],"pdf":[],"categories":["Architecture magazines","Publications established in 1961","German-language magazines","English-language magazines","Reed Elsevier"],"headings":["History","Brief description","Content","Publication","Circulation","Readership","DETAIL internationally","DETAIL Network","External links"],"image":["//upload.wikimedia.org/wikipedia/en/thumb/4/48/Folder_Hexagonal_Icon.svg/16px-Folder_Hexagonal_Icon.svg.png","//bits.wikimedia.org/static-1.21wmf10/skins/vector/images/search-ltr.png?303-4","//bits.wikimedia.org/images/wikimedia-button.png","//bits.wikimedia.org/static-1.21wmf10/skins/common/images/poweredby_mediawiki_88x31.png"],"tags":[],"members":[],"related":["Architecture","Architect","Engineer"]}