{"cursor":"3665","size":15,"audio":[],"currentlang":"en","article":"{{Infobox Album \n| Name = Destination Type = studio Artist = FictionJunction Yuuka Cover =\n| Released = November 23, 2005 Recorded = 2005 Genre = Japanese pop Length =\n| 49:02 Label = Victor Entertainment VICL-61792 (Japan, CD) VIZL-\n| 159 (Japan, CD+DVD) | Producer = Victor Entertainment Reviews = Last\n| album = | This album = 'Destination' (2005) Next album = [[Circus\n| (FictionJunction Yuuka album)|Circus]] (2007)\n}}\n\n'Destination' is the first album of J-pop duo FictionJunction Yuuka. It was\nreleased on November 23, 2005.\n\nThis album includes their first three singles and their b-sides, as well as five\nbrand-new songs. There are two versions of this album: the normal edition (with\ncatalog number VICL-61792) and the limited edition. The limited edition, with\nthe catalog number VIZL-159, includes a DVD with the PV of Honoh no Tobira, its\nmaking of and a commercial for the single (15 seconds and 30 seconds).\n\nThe album, at its peak, ranked ninth on the Oricon\ncharts. [http://www.oricon.co.jp/music/release/d/623194/1/ Destination at\nOricon Style.] Retrieved 2007-03-09.\n","linknr":150,"url":"Destination_(FictionJunction_Yuuka_album)","recorded":1364039360,"links":["/w/index.php?title=Destination_(FictionJunction_Yuuka_album)&action=edit","/w/index.php?title=Destination_(FictionJunction_Yuuka_album)&action=edit","//en.wikipedia.org/apple-touch-icon.png","//bits.wikimedia.org/favicon/wikipedia.ico","/w/opensearch_desc.php","//en.wikipedia.org/w/api.php?action=rsd","//creativecommons.org/licenses/by-sa/3.0/","/w/index.php?title=Special:RecentChanges&feed=atom","//bits.wikimedia.org/en.wikipedia.org/load.php?debug=false&lang=en&modules=ext.gadget.DRN-wizard%2CReferenceTooltips%2Ccharinsert%2Cteahouse%7Cext.wikihiero%7Cmediawiki.legacy.commonPrint%2Cshared%7Cmw.PopUpMediaTransform%7Cskins.vector&only=styles&skin=vector&*","//bits.wikimedia.org/en.wikipedia.org/load.php?debug=false&lang=en&modules=site&only=styles&skin=vector&*","//bits.wikimedia.org/en.wikipedia.org/load.php?debug=false&lang=en&modules=startup&only=scripts&skin=vector&*","//bits.wikimedia.org/geoiplookup","//meta.wikimedia.org","#mw-head","#p-search","/wiki/Studio_album","/wiki/FictionJunction_Yuuka","/wiki/Music_genre","/wiki/J-pop","/wiki/Record_label","/wiki/Victor_Entertainment","/wiki/Japan","/wiki/Record_producer","/wiki/Victor_Entertainment","/wiki/FictionJunction_Yuuka","/wiki/Circus_(FictionJunction_Yuuka_album)","/wiki/J-pop","/wiki/FictionJunction_Yuuka","/wiki/B-sides","/wiki/Promotional_Video","/wiki/Honoh_no_Tobira","/wiki/Making_of","/wiki/Oricon","#cite_note-1","#Track_listings","#CD.5B2.5D","#Track_listing","#DVD.5B3.5D","#External_links","#References_and_notes","/w/index.php?title=Destination_(FictionJunction_Yuuka_album)&action=edit&section=1","/w/index.php?title=Destination_(FictionJunction_Yuuka_album)&action=edit&section=2","#cite_note-2","/w/index.php?title=Destination_(FictionJunction_Yuuka_album)&action=edit&section=3","/wiki/Yuki_Kajiura","/wiki/Madlax","/wiki/Akatsuki_no_Kuruma","/wiki/Help:Installing_Japanese_character_sets","/wiki/Mobile_Suit_Gundam_Seed","/wiki/Help:Installing_Japanese_character_sets","/wiki/Help:Installing_Japanese_character_sets","/wiki/Help:Installing_Japanese_character_sets","/wiki/Help:Installing_Japanese_character_sets","/wiki/Hitomi_no_Kakera","/wiki/Help:Installing_Japanese_character_sets","/wiki/Inside_Your_Heart","/w/index.php?title=Destination_(FictionJunction_Yuuka_album)&action=edit&section=4","#cite_note-3","/wiki/Honoo_no_Tobira","/w/index.php?title=Destination_(FictionJunction_Yuuka_album)&action=edit&section=5","http://www.jvcmusic.co.jp/-/Discography/A018153/VICL-61792.html","/w/index.php?title=Destination_(FictionJunction_Yuuka_album)&action=edit&section=6","#cite_ref-1","http://www.oricon.co.jp/music/release/d/623194/1/","#cite_ref-2","http://www.jvcmusic.co.jp/-/Discography/A018153/VICL-61792.html","#cite_ref-3","http://www.jvcmusic.co.jp/-/Discography/A018153/VIZL-159.html","/wiki/Template:FictionJunction_Yuuka","/wiki/Template_talk:FictionJunction_Yuuka","//en.wikipedia.org/w/index.php?title=Template:FictionJunction_Yuuka&action=edit","/wiki/FictionJunction_Yuuka","/wiki/Yuki_Kajiura","/wiki/Yuuka_Nanri","/wiki/Hitomi_no_Kakera","/wiki/Inside_Your_Heart","/wiki/Akatsuki_no_Kuruma","/wiki/Honoh_no_Tobira","/wiki/Silly-Go-Round","/wiki/K%C5%8Dya_Ruten","/wiki/Romanesque_(song)","/wiki/Circus_(FictionJunction_Yuuka_album)","/wiki/FictionJunction","/wiki/See-Saw","/wiki/Tiaraway","/wiki/File:Gnome-dev-cdrom-audio.svg","//upload.wikimedia.org/wikipedia/commons/thumb/b/b0/Gnome-dev-cdrom-audio.svg/32px-Gnome-dev-cdrom-audio.svg.png","/wiki/Wikipedia:Stub","//en.wikipedia.org/w/index.php?title=Destination_(FictionJunction_Yuuka_album)&action=edit","/wiki/Template:Japan-album-stub","/wiki/Template_talk:Japan-album-stub","//en.wikipedia.org/w/index.php?title=Template:Japan-album-stub&action=edit","http://en.wikipedia.org/w/index.php?title=Destination_(FictionJunction_Yuuka_album)&oldid=544682171","/wiki/Help:Categories","/wiki/Category:2005_albums","/wiki/Category:Victor_Entertainment_albums","/wiki/Category:Japan_album_stubs","/wiki/Category:Articles_with_hAudio_microformats","/wiki/Category:Album_infoboxes_lacking_a_cover","/wiki/Category:Articles_containing_Japanese_language_text","/w/index.php?title=Special:UserLogin&returnto=Destination+%28FictionJunction+Yuuka+album%29&type=signup","/w/index.php?title=Special:UserLogin&returnto=Destination+%28FictionJunction+Yuuka+album%29","/wiki/Destination_(FictionJunction_Yuuka_album)","/wiki/Talk:Destination_(FictionJunction_Yuuka_album)","#","/wiki/Destination_(FictionJunction_Yuuka_album)","/w/index.php?title=Destination_(FictionJunction_Yuuka_album)&action=edit","/w/index.php?title=Destination_(FictionJunction_Yuuka_album)&action=history","#","/w/index.php","//bits.wikimedia.org/static-1.21wmf11/skins/vector/images/search-ltr.png?303-4","/wiki/Main_Page","/wiki/Main_Page","/wiki/Portal:Contents","/wiki/Portal:Featured_content","/wiki/Portal:Current_events","/wiki/Special:Random","//donate.wikimedia.org/wiki/Special:FundraiserRedirector?utm_source=donate&utm_medium=sidebar&utm_campaign=C13_en.wikipedia.org&uselang=en","/wiki/Help:Contents","/wiki/Wikipedia:About","/wiki/Wikipedia:Community_portal","/wiki/Special:RecentChanges","/wiki/Wikipedia:Contact_us","/wiki/Special:WhatLinksHere/Destination_(FictionJunction_Yuuka_album)","/wiki/Special:RecentChangesLinked/Destination_(FictionJunction_Yuuka_album)","/wiki/Wikipedia:File_Upload_Wizard","/wiki/Special:SpecialPages","/w/index.php?title=Destination_(FictionJunction_Yuuka_album)&oldid=544682171","/w/index.php?title=Destination_(FictionJunction_Yuuka_album)&action=info","/w/index.php?title=Special:Cite&page=Destination_%28FictionJunction_Yuuka_album%29&id=544682171","/w/index.php?title=Special:Book&bookcmd=book_creator&referer=Destination+%28FictionJunction+Yuuka+album%29","/w/index.php?title=Special:Book&bookcmd=render_article&arttitle=Destination+%28FictionJunction+Yuuka+album%29&oldid=544682171&writer=rl","/w/index.php?title=Destination_(FictionJunction_Yuuka_album)&printable=yes","//ja.wikipedia.org/wiki/Destination_(FictionJunction_YUUKA%E3%81%AE%E3%82%A2%E3%83%AB%E3%83%90%E3%83%A0)","//www.wikidata.org/wiki/Special:ItemByTitle/enwiki/Destination (FictionJunction Yuuka album)","//en.wikipedia.org/wiki/Wikipedia:Text_of_Creative_Commons_Attribution-ShareAlike_3.0_Unported_License","//creativecommons.org/licenses/by-sa/3.0/","//wikimediafoundation.org/wiki/Terms_of_Use","//www.wikimediafoundation.org/","//en.wikipedia.org/wiki/Wikipedia:Contact_us","//wikimediafoundation.org/wiki/Privacy_policy","/wiki/Wikipedia:About","/wiki/Wikipedia:General_disclaimer","http://en.m.wikipedia.org/wiki/Destination_(FictionJunction_Yuuka_album)","//wikimediafoundation.org/","//bits.wikimedia.org/images/wikimedia-button.png","//www.mediawiki.org/","//bits.wikimedia.org/static-1.21wmf11/skins/common/images/poweredby_mediawiki_88x31.png","//bits.wikimedia.org/en.wikipedia.org/load.php?debug=false&lang=en&modules=skins.vector&only=scripts&skin=vector&*","/w/index.php?title=MediaWiki:Gadget-ReferenceTooltips.js&action=raw&ctype=text/javascript&508635914","//bits.wikimedia.org/en.wikipedia.org/load.php?debug=false&lang=en&modules=site&only=scripts&skin=vector&*"],"instances":[],"pdf":[],"categories":["2005 albums","Victor Entertainment albums"],"headings":["Track listings","Track listing","External links","References and notes"],"image":["//upload.wikimedia.org/wikipedia/commons/thumb/b/b0/Gnome-dev-cdrom-audio.svg/32px-Gnome-dev-cdrom-audio.svg.png","//bits.wikimedia.org/static-1.21wmf11/skins/vector/images/search-ltr.png?303-4","//bits.wikimedia.org/images/wikimedia-button.png","//bits.wikimedia.org/static-1.21wmf11/skins/common/images/poweredby_mediawiki_88x31.png"],"tags":[],"members":[],"related":["FictionJunction_Yuuka","J-pop","Victor_Entertainment","Japan","Victor_Entertainment","J-pop","FictionJunction_Yuuka","B-sides","Promotional_Video","Honoh_no_Tobira","Making_of","Oricon","Yuki_Kajiura","Madlax","Mobile_Suit_Gundam_Seed","Inside_Your_Heart","Honoo_no_Tobira"]}