{"cursor":"534","size":15,"audio":[],"currentlang":"en","article":"\n\n'HPC' is an abbreviation for 'hydroprocessing'. HPC catalysts are catalysts used\nin the hydroprocessing of crude oil fractions like naphtha, kero and diesel\nunder elevated pressure and temperature. Hydroprocessing is necessary to remove\npollutants like sulfur, nitrogen and heavy metals from fuel oils, as well as in\nthe process of catalytic hydrocracking, where large hydrocarbon molecules are\ncracked into shorter ones that can be used as fuel oils.\n","linknr":92,"url":"Hydroprocessing","recorded":1362500039,"links":13,"instances":[],"pdf":[],"categories":["Oil refining"],"headings":[],"image":["//upload.wikimedia.org/wikipedia/commons/thumb/f/f8/Edit-copy_purple-wikit.svg/40px-Edit-copy_purple-wikit.svg.png","//upload.wikimedia.org/wikipedia/en/thumb/9/99/Question_book-new.svg/50px-Question_book-new.svg.png","//bits.wikimedia.org/static-1.21wmf10/skins/vector/images/search-ltr.png?303-4","//bits.wikimedia.org/images/wikimedia-button.png","//bits.wikimedia.org/static-1.21wmf10/skins/common/images/poweredby_mediawiki_88x31.png"],"tags":[],"members":[],"related":["Hydroprocessing","Hydrocracking"]}